<?xml version="1.0" encoding="ISO-8859-1"?>
<objectpool>
  <workingset name="wsTutorialDisplay" id="0" background_colour="white" selectable="1" active_mask="dmAbout">
    <outputstring name="osWsDesc" id="555" width="70" height="30" font_attributes="fta8x12_SK" background_colour="white" options="transparent+autowrap" horizontal_justification="middle" vertical_justification="top" value="TutDisplay" length="10" auto_set_length="1" variable_reference="NULL" pos_x="-3" pos_y="11"/>
    <language code="de"/>
    <language code="en"/>
  </workingset>
  <macro name="macroChangeMaskAbout" id="252" number_of_bytes="8">
    <command_change_active_mask working_set_object_id="wsTutorialDisplay" new_active_mask_object_id="dmAbout"/>
  </macro>
  <macro name="macroChangeMaskTecu" id="254" number_of_bytes="8">
    <command_change_active_mask working_set_object_id="wsTutorialDisplay" new_active_mask_object_id="dmTecu"/>
  </macro>
  <macro name="macroChangeMaskTimePos" id="255" number_of_bytes="8">
    <command_change_active_mask working_set_object_id="wsTutorialDisplay" new_active_mask_object_id="dmTimePos"/>
  </macro>
  <datamask name="dmTimePos" id="1000" background_colour="white" soft_key_mask="skmDisplay">
    <include_object name="ctnIsoAgLib" pos_x="0" pos_y="0"/>
    <include_object name="osMaskTimePos" pos_x="115" pos_y="15"/>
    <include_object name="ctnDirectionDisplay" pos_x="18" pos_y="34"/>
    <include_object name="ctnLon" pos_x="103" pos_y="35"/>
    <include_object name="ctnLat" pos_x="3" pos_y="35"/>
  </datamask>
  <datamask name="dmTecu" id="1001" background_colour="222" soft_key_mask="skmDisplay">
    <include_object name="ctnIsoAgLib" pos_x="0" pos_y="0"/>
    <include_object name="ctnKeySwitch" pos_x="2" pos_y="168"/>
    <include_object name="ctnDistReal" pos_x="2" pos_y="185"/>
    <include_object name="ctnPto" pos_x="2" pos_y="121"/>
    <include_object name="ctnMaxPower" pos_x="2" pos_y="153"/>
    <include_object name="ctrHitch" pos_x="102" pos_y="35"/>
    <include_object name="ctrSpeed" pos_x="2" pos_y="35"/>
    <include_object name="osMaskTecu" pos_x="115" pos_y="15"/>
  </datamask>
  <datamask name="dmAbout" id="1004" background_colour="222" soft_key_mask="skmDisplay">
    <include_object name="ctnAbout" pos_x="4" pos_y="60"/>
    <include_object name="ctnIsoAgLib" pos_x="0" pos_y="0"/>
    <include_object name="osAboutTitle" pos_x="115" pos_y="8"/>
  </datamask>
  <container name="ctnMaxPower" id="2000" width="200" height="13" hidden="0">
    <include_object name="rctMaxPower" pos_x="0" pos_y="0"/>
    <include_object name="osMaxPower" pos_x="2" pos_y="2"/>
    <include_object name="onMaxPowerTime" pos_x="125" pos_y="2"/>
    <include_object name="osMin" pos_x="170" pos_y="2"/>
  </container>
  <container name="ctnLat" id="2001" width="97" height="26" hidden="0">
    <include_object name="osLat" pos_x="0" pos_y="0"/>
    <include_object name="onLat" pos_x="0" pos_y="11"/>
  </container>
  <container name="ctnLon" id="2002" width="97" height="20" hidden="0">
    <include_object name="osLon" pos_x="35" pos_y="0"/>
    <include_object name="onLon" pos_x="35" pos_y="11"/>
  </container>
  <container name="ctnKeySwitch" id="2003" width="200" height="13" hidden="0">
    <include_object name="rctKeySwitch" pos_x="0" pos_y="0"/>
    <include_object name="osKeySwitch" pos_x="2" pos_y="2"/>
    <include_object name="opKeySwitch" pos_x="157" pos_y="2"/>
  </container>
  <container name="ctnIsoAgLib" id="2004" width="200" height="33" hidden="0">
    <include_object name="recLogoFrame" pos_x="0" pos_y="0"/>
    <include_object name="picIsoAgLib" pos_x="0" pos_y="0"/>
  </container>
  <container name="ctnTime" id="2008" width="250" height="20" hidden="0">
    <include_object name="rctTime" pos_x="0" pos_y="0"/>
    <include_object name="osTime" pos_x="4" pos_y="6"/>
    <include_object name="ctnTimeValue" pos_x="100" pos_y="6"/>
  </container>
  <container name="ctnPtoFront" id="2009" width="196" height="14" hidden="0">
    <include_object name="osPtoFront" pos_x="2" pos_y="3"/>
    <include_object name="onPtoFront" pos_x="65" pos_y="3"/>
    <include_object name="lbPtoFront" pos_x="130" pos_y="2"/>
    <include_object name="opPtoFrontEngaged" pos_x="115" pos_y="2"/>
    <include_object name="osRpm" pos_x="91" pos_y="3"/>
  </container>
  <container name="ctnPtoRear" id="2010" width="196" height="14" hidden="0">
    <include_object name="osPtoRear" pos_x="2" pos_y="3"/>
    <include_object name="onPtoRear" pos_x="65" pos_y="3"/>
    <include_object name="lbPtoRear" pos_x="130" pos_y="2"/>
    <include_object name="opPtoRearEngaged" pos_x="115" pos_y="2"/>
    <include_object name="osRpm" pos_x="91" pos_y="3"/>
  </container>
  <container name="ctnSpeedReal" id="2011" width="95" height="10" hidden="0">
    <include_object name="osSpeedReal" pos_x="2" pos_y="0"/>
    <include_object name="onSpeedReal" pos_x="44" pos_y="0"/>
    <include_object name="osCmS" pos_x="66" pos_y="0"/>
  </container>
  <container name="ctnDistReal" id="2012" width="197" height="13" hidden="0">
    <include_object name="rctDistReal" pos_x="0" pos_y="0"/>
    <include_object name="osDistReal" pos_x="2" pos_y="2"/>
    <include_object name="onDistReal" pos_x="125" pos_y="2"/>
    <include_object name="osM" pos_x="170" pos_y="2"/>
  </container>
  <container name="ctnTimeValue" id="2013" width="90" height="13" hidden="0">
    <include_object name="onTimeH" pos_x="10" pos_y="2"/>
    <include_object name="osColon" pos_x="30" pos_y="2"/>
    <include_object name="onTimeM" pos_x="40" pos_y="2"/>
    <include_object name="osColon" pos_x="60" pos_y="2"/>
    <include_object name="onTimeS" pos_x="70" pos_y="2"/>
  </container>
  <container name="ctnIsoaglibVersion" id="2014" width="192" height="20" hidden="0">
    <include_object name="rctIsoAgLibVersion" pos_x="0" pos_y="0"/>
    <include_object name="osIsoAgLibVersionLabel" pos_x="4" pos_y="6"/>
    <include_object name="osIsoaglibVersion" pos_x="108" pos_y="6"/>
  </container>
  <container name="ctnTutorialVersion" id="2015" width="250" height="20" hidden="0">
    <include_object name="rctTutorialVersion" pos_x="0" pos_y="0"/>
    <include_object name="osTutorialVersionLabel" pos_x="4" pos_y="6"/>
    <include_object name="osTutorialVersion" pos_x="108" pos_y="6"/>
  </container>
  <container name="ctnBuildDate" id="2016" width="250" height="20" hidden="0">
    <include_object name="rctBuildDate" pos_x="0" pos_y="0"/>
    <include_object name="osBuildDateLabel" pos_x="4" pos_y="6"/>
    <include_object name="osBuildDate" pos_x="108" pos_y="6"/>
  </container>
  <container name="ctnAbout" id="2017" width="192" height="120" hidden="0">
    <include_object name="ctnIsoaglibVersion" pos_x="0" pos_y="0"/>
    <include_object name="ctnTutorialVersion" pos_x="0" pos_y="30"/>
    <include_object name="ctnBuildDate" pos_x="0" pos_y="60"/>
    <include_object name="ctnTime" pos_x="0" pos_y="90"/>
  </container>
  <container name="ctnSpeedDisplay" id="2018" width="90" height="61" hidden="0">
    <include_object name="abgSpeed" pos_x="10" pos_y="30"/>
    <include_object name="opsSpeed0" pos_x="3" pos_y="54"/>
    <include_object name="opsSpeed150" pos_x="24" pos_y="22"/>
    <include_object name="opsSpeed300" pos_x="68" pos_y="54"/>
    <include_object name="mtrSpeed" pos_x="10" pos_y="30"/>
  </container>
  <container name="ctnPto" id="2019" width="200" height="28" hidden="0">
    <include_object name="rctPto" pos_x="0" pos_y="0"/>
    <include_object name="ctnPtoFront" pos_x="0" pos_y="0"/>
    <include_object name="ctnPtoRear" pos_x="0" pos_y="14"/>
  </container>
  <container name="ctnDirectionDisplay" id="3000" width="165" height="165" hidden="0">
    <include_object name="picWindrose" pos_x="0" pos_y="0"/>
    <include_object name="mtrDirection" pos_x="15" pos_y="15"/>
  </container>
  <container name="ctrHitchSetCurTrgt" id="3001" width="40" height="15" hidden="0">
    <include_object name="btnHitchSetCurTrgt" pos_x="0" pos_y="0"/>
    <include_object name="opsHitchSetTrgtBtnLabel" pos_x="4" pos_y="4"/>
  </container>
  <container name="ctrHitchGraphDisplay" id="3002" width="62" height="62" hidden="0">
    <include_object name="abgHitch" pos_x="16" pos_y="2"/>
    <include_object name="mtrHitch" pos_x="16" pos_y="2"/>
    <include_object name="opsHitch0Deg" pos_x="2" pos_y="30"/>
    <include_object name="opsHitchMinus45Deg" pos_x="10" pos_y="56"/>
    <include_object name="opsHitchPlus45Deg" pos_x="10" pos_y="3"/>
  </container>
  <container name="ctrHitchTrgtStrDisplay" id="3003" width="120" height="26" hidden="0">
    <include_object name="opsHitchTargetAngle" pos_x="2" pos_y="0"/>
    <include_object name="opnHitchTargetAngle" pos_x="47" pos_y="0"/>
    <include_object name="opsHItchDegree" pos_x="65" pos_y="0"/>
  </container>
  <container name="ctrHitch" id="3005" width="97" height="83" hidden="0">
    <include_object name="rctHitch" pos_x="0" pos_y="0"/>
    <include_object name="ctrHitchGraphDisplay" pos_x="2" pos_y="4"/>
    <include_object name="ctrHitchTrgtStrDisplay" pos_x="2" pos_y="72"/>
    <include_object name="picHitch" pos_x="76" pos_y="3"/>
    <include_object name="ctrHitchSetCurTrgt" pos_x="52" pos_y="46"/>
  </container>
  <container name="ctrSpeed" id="3006" width="97" height="83" hidden="0">
    <include_object name="rctSpeed" pos_x="0" pos_y="0"/>
    <include_object name="ctnSpeedDisplay" pos_x="2" pos_y="5"/>
    <include_object name="ctnSpeedReal" pos_x="0" pos_y="72"/>
    <include_object name="picSpeed" pos_x="72" pos_y="3"/>
  </container>
  <button name="btnHitchSetCurTrgt" id="6000" width="40" height="15" background_colour="42" border_colour="black" key_code="253" options="none"/>
  <outputnumber name="opnHitchTargetAngle" id="12001" width="18" height="10" font_attributes="fta6x8" background_colour="white" options="transparent" number_of_decimals="0" format="fixed" horizontal_justification="right" vertical_justification="top" offset="-45" scale="1" value="0" variable_reference="nvHitchAngleTarget"/>
  <rectangle name="rctHitch" id="14000" width="97" height="83" line_attributes="lnSolidBlack" fill_attributes="flaContentBg" line_suppression="none"/>
  <rectangle name="rctSpeed" id="14001" width="97" height="83" line_attributes="lnSolidBlack" fill_attributes="flaContentBg" line_suppression="none"/>
  <rectangle name="rctIsoAgLibVersion" id="14002" width="192" height="20" line_attributes="lnSolidBlack" fill_attributes="flaContentBg" line_suppression="none"/>
  <rectangle name="rctTutorialVersion" id="14003" width="192" height="20" line_attributes="lnSolidBlack" fill_attributes="flaContentBg" line_suppression="none"/>
  <rectangle name="rctPto" id="14004" width="197" height="28" line_attributes="lnSolidBlack" fill_attributes="flaContentBg" line_suppression="none"/>
  <rectangle name="rctMaxPower" id="14005" width="197" height="13" line_attributes="lnSolidBlack" fill_attributes="flaContentBg" line_suppression="none"/>
  <rectangle name="rctKeySwitch" id="14006" width="197" height="13" line_attributes="lnSolidBlack" fill_attributes="flaContentBg" line_suppression="none"/>
  <rectangle name="rctDistReal" id="14007" width="197" height="13" line_attributes="lnSolidBlack" fill_attributes="flaContentBg" line_suppression="none"/>
  <rectangle name="rctBuildDate" id="14008" width="192" height="20" line_attributes="lnSolidBlack" fill_attributes="flaContentBg" line_suppression="none"/>
  <rectangle name="rctTime" id="14009" width="192" height="20" line_attributes="lnSolidBlack" fill_attributes="flaContentBg" line_suppression="none"/>
  <meter name="mtrDirection" id="17000" width="136" min_value="0" max_value="360" needle_colour="blue" border_colour="white" arc_and_tick_colour="navy" number_of_ticks="36" options="clockwise" start_angle="45" end_angle="45" value="0" variable_reference="NULL"/>
  <meter name="mtrHitch" id="17002" width="62" min_value="0" max_value="90" needle_colour="20" border_colour="black" arc_and_tick_colour="black" number_of_ticks="9" options="arc+ticks+clockwise" start_angle="68" end_angle="112" value="70" variable_reference="nvHitchAngleTarget"/>
  <archedbargraph name="abgSpeed" id="19000" width="56" height="56" bar_graph_width="10" min_value="0" max_value="300" colour="maroon" target_line_colour="maroon" options="border+clockwise" start_angle="0" end_angle="90" value="0" variable_reference="nvSpeedReal" target_value="0" target_value_variable_reference="NULL"/>
  <archedbargraph name="abgHitch" id="19001" width="62" height="62" bar_graph_width="10" min_value="0" max_value="90" colour="teal" target_line_colour="blue" options="border+targetline+clockwise" start_angle="68" end_angle="112" value="9" variable_reference="nvHitchAngle" target_value="0" target_value_variable_reference="nvHitchAngleTarget"/>
  <picturegraphic name="picWindrose" id="20000" width="166" options="transparent" transparency_colour="white" file1="compass_card_bw.bmp" file4="compass_card_color.bmp" file8="compass_card_color.bmp" abs_path1="0" abs_path4="0" abs_path8="0" height="208" number_of_bytes=""/>
  <picturegraphic name="picIsoAgLib" id="20001" width="200" options="transparent" transparency_colour="white" file1="isoaglib.bmp" file4="isoaglib.bmp" file8="isoaglib.bmp" abs_path1="0" abs_path4="0" abs_path8="0" number_of_bytes=""/>
  <picturegraphic name="picHitch" id="20002" width="18" options="transparent" transparency_colour="white" file1="hitch.bmp" file4="hitch.bmp" file8="hitch.bmp" abs_path1="0" abs_path4="0" abs_path8="0" height="77" number_of_bytes=""/>
  <picturegraphic name="picSpeed" id="20003" width="22" options="transparent" transparency_colour="white" file1="tractor_speed.bmp" file4="tractor_speed.bmp" file8="tractor_speed.bmp" abs_path1="0" abs_path4="0" abs_path8="0" number_of_bytes=""/>
  <picturegraphic name="picKeyNavTecu" id="20004" width="32" options="transparent" transparency_colour="white" file1="navi_key_tecu.bmp" file4="navi_key_tecu.bmp" file8="navi_key_tecu.bmp" abs_path1="0" abs_path4="0" abs_path8="0" number_of_bytes=""/>
  <picturegraphic name="picKeyNavTimePos" id="20005" width="32" options="transparent" transparency_colour="white" file1="navi_key_gps.bmp" file4="navi_key_gps.bmp" file8="navi_key_gps.bmp" abs_path1="0" abs_path4="0" abs_path8="0" number_of_bytes=""/>
  <picturegraphic name="picKeyNavAbout" id="20006" width="32" options="transparent" transparency_colour="white" file1="navi_key_about.bmp" file4="navi_key_about.bmp" file8="navi_key_about.bmp" abs_path1="0" abs_path4="0" abs_path8="0" number_of_bytes=""/>
  <numbervariable name="nvHitchAngle" id="21000" value="0"/>
  <numbervariable name="nvHitchAngleTarget" id="21001" value="0"/>
  <outputstring name="opsHitchTargetAngle" id="40002" width="70" height="10" font_attributes="fta6x8" background_colour="white" options="transparent+autowrap" horizontal_justification="left" vertical_justification="top" value="Target:" length="7" auto_set_length="1" variable_reference="NULL"/>
  <outputstring name="opsHItchDegree" id="40003" width="10" height="10" font_attributes="fta6x8" background_colour="white" options="transparent+autowrap" horizontal_justification="left" vertical_justification="top" value="°" length="1" auto_set_length="1" variable_reference="NULL"/>
  <outputstring name="opsHitchPlus45Deg" id="40004" width="40" height="12" font_attributes="fta6x8" background_colour="white" options="transparent+autowrap" horizontal_justification="left" vertical_justification="top" value=" 45°" length="4" auto_set_length="1" variable_reference="NULL"/>
  <outputstring name="opsHitchMinus45Deg" id="40005" width="40" height="121" font_attributes="fta6x8" background_colour="white" options="transparent+autowrap" horizontal_justification="left" vertical_justification="top" value="-45°" length="4" auto_set_length="1" variable_reference="NULL"/>
  <outputstring name="opsHitch0Deg" id="40006" width="11" height="11" font_attributes="fta6x8" background_colour="white" options="transparent+autowrap" horizontal_justification="left" vertical_justification="top" value="0" length="1" auto_set_length="1" variable_reference="NULL"/>
  <outputstring name="opsHitchSetTrgtBtnLabel" id="40009" width="35" height="8" font_attributes="fta8x8" background_colour="white" options="transparent+autowrap" horizontal_justification="left" vertical_justification="top" value="Save" length="4" auto_set_length="1" variable_reference="NULL"/>
  <outputstring name="opsSpeed0" id="40011" width="6" height="8" font_attributes="fta6x8" background_colour="white" options="transparent+autowrap" horizontal_justification="right" vertical_justification="top" value="0" length="1" auto_set_length="1" variable_reference="NULL"/>
  <outputstring name="opsSpeed150" id="40012" width="27" height="6" font_attributes="fta6x8" background_colour="white" options="transparent+autowrap" horizontal_justification="middle" vertical_justification="top" value="150" length="3" auto_set_length="1" variable_reference="NULL"/>
  <outputstring name="opsSpeed300" id="40014" width="20" height="8" font_attributes="fta6x8" background_colour="white" options="transparent+autowrap" horizontal_justification="left" vertical_justification="top" value="300" length="3" auto_set_length="1" variable_reference="NULL"/>
  <outputstring name="osRpm" id="65458" width="20" height="10" font_attributes="fta6x8" background_colour="white" options="transparent+autowrap" horizontal_justification="left" vertical_justification="top" value="rpm" length="3" auto_set_length="1" variable_reference="NULL"/>
  <objectpointer name="opPtoRearEngaged" id="65459" value="elStateRed"/>
  <objectpointer name="opPtoFrontEngaged" id="65460" value="elStateRed"/>
  <outputstring name="osBuildDate" id="65464" width="80" height="10" font_attributes="fta6x8" background_colour="white" options="transparent+autowrap" horizontal_justification="right" vertical_justification="top" value="                    " length="20" auto_set_length="1" variable_reference="NULL"/>
  <outputstring name="osBuildDateLabel" id="65465" language="*" width="120" height="10" font_attributes="fta6x8" background_colour="white" options="transparent+autowrap" horizontal_justification="left" vertical_justification="top" value="" length="0" auto_set_length="1" variable_reference="NULL"/>
  <outputstring name="osTutorialVersion" id="65466" width="80" height="10" font_attributes="fta6x8" background_colour="white" options="transparent+autowrap" horizontal_justification="right" vertical_justification="top" value="0.0.0" length="5" auto_set_length="0" variable_reference="NULL"/>
  <outputstring name="osTutorialVersionLabel" id="65467" language="*" width="110" height="10" font_attributes="fta6x8" background_colour="white" options="transparent+autowrap" horizontal_justification="left" vertical_justification="top" value="" length="0" auto_set_length="1" variable_reference="NULL"/>
  <outputstring name="osIsoaglibVersion" id="65468" width="80" height="10" font_attributes="fta6x8" background_colour="white" options="transparent+autowrap" horizontal_justification="right" vertical_justification="top" value="0.0.0" length="5" auto_set_length="0" variable_reference="NULL"/>
  <outputstring name="osIsoAgLibVersionLabel" id="65469" language="*" width="120" height="10" font_attributes="fta6x8" background_colour="white" options="transparent+autowrap" horizontal_justification="left" vertical_justification="top" value="ISOAGLib Version" length="16" auto_set_length="1" variable_reference="NULL"/>
  <outputstring name="osColon" id="65470" width="10" height="10" font_attributes="fta6x8" background_colour="white" options="transparent+autowrap" horizontal_justification="middle" vertical_justification="top" value=":" length="1" auto_set_length="1" variable_reference="NULL"/>
  <outputnumber name="onTimeS" id="65471" width="20" height="10" font_attributes="fta6x8" background_colour="white" options="transparent" number_of_decimals="0" format="fixed" horizontal_justification="middle" vertical_justification="top" offset="0" scale="1" value="0" variable_reference="nvSec"/>
  <ellipse name="elStateGreen" id="65472" width="10" height="10" line_attributes="lnSolidBlack" fill_attributes="flaOk" ellipse_type="closed" start_angle="0" end_angle="180"/>
  <linearbargraph name="lbPtoRear" id="65473" width="63" height="10" min_value="0" max_value="1200" colour="black" target_line_colour="black" options="border+ticks+horizontal+growpositive" number_of_ticks="10" value="0" variable_reference="nvPtoRear" target_value="50" target_value_variable_reference="NULL"/>
  <linearbargraph name="lbPtoFront" id="65474" width="63" height="10" min_value="0" max_value="1200" colour="black" target_line_colour="black" options="border+ticks+horizontal+growpositive" number_of_ticks="10" value="0" variable_reference="nvPtoFront" target_value="50" target_value_variable_reference="NULL"/>
  <numbervariable name="nvSpeedTheor" id="65476" value="0"/>
  <numbervariable name="nvDistTheor" id="65477" value="0"/>
  <numbervariable name="nvMaxPowerTime" id="65478" value="0"/>
  <numbervariable name="nvDistReal" id="65479" value="0"/>
  <outputnumber name="onDistReal" id="65480" width="40" height="9" font_attributes="fta6x8" background_colour="white" options="transparent" number_of_decimals="0" format="fixed" horizontal_justification="right" vertical_justification="top" offset="0" scale="1" value="0" variable_reference="nvDistReal"/>
  <outputstring name="osDistReal" id="65481" width="100" height="8" font_attributes="fta6x8" background_colour="white" options="transparent+autowrap" horizontal_justification="left" vertical_justification="top" value="Distance:" length="9" auto_set_length="1" variable_reference="NULL"/>
  <numbervariable name="nvSpeedReal" id="65482" value="0"/>
  <outputnumber name="onSpeedReal" id="65483" width="20" height="10" font_attributes="fta6x8" background_colour="white" options="transparent" number_of_decimals="0" format="fixed" horizontal_justification="left" vertical_justification="top" offset="0" scale="1" value="0" variable_reference="nvSpeedReal"/>
  <outputstring name="osSpeedReal" id="65484" width="36" height="10" font_attributes="fta6x8" background_colour="white" options="transparent+autowrap" horizontal_justification="left" vertical_justification="top" value="Speed:" length="6" auto_set_length="1" variable_reference="NULL"/>
  <numbervariable name="nvPtoRear" id="65485" value="0"/>
  <outputnumber name="onPtoRear" id="65486" width="25" height="10" font_attributes="fta6x8" background_colour="white" options="transparent" number_of_decimals="0" format="fixed" horizontal_justification="right" vertical_justification="top" offset="0" scale="1" value="0" variable_reference="nvPtoRear"/>
  <outputstring name="osPtoRear" id="65487" width="55" height="10" font_attributes="fta6x8" background_colour="white" options="transparent+autowrap" horizontal_justification="left" vertical_justification="top" value="PTO Rear:" length="9" auto_set_length="1" variable_reference="NULL"/>
  <numbervariable name="nvPtoFront" id="65488" value="0"/>
  <outputnumber name="onPtoFront" id="65489" width="25" height="10" font_attributes="fta6x8" background_colour="white" options="transparent" number_of_decimals="0" format="fixed" horizontal_justification="right" vertical_justification="top" offset="0" scale="1" value="0" variable_reference="nvPtoFront"/>
  <outputstring name="osAboutTitle" id="65490" width="80" height="15" font_attributes="fta8x8" background_colour="white" options="transparent+autowrap" horizontal_justification="middle" vertical_justification="top" value="ISOAgLib Tutorial" length="17" auto_set_length="1" variable_reference="NULL"/>
  <outputstring name="osM" id="65494" width="18" height="10" font_attributes="fta6x8" background_colour="white" options="transparent+autowrap" horizontal_justification="left" vertical_justification="top" value="m" length="1" auto_set_length="1" variable_reference="NULL"/>
  <outputstring name="osMin" id="65496" width="18" height="10" font_attributes="fta6x8" background_colour="white" options="transparent+autowrap" horizontal_justification="left" vertical_justification="top" value="min" length="3" auto_set_length="1" variable_reference="NULL"/>
  <ellipse name="elStateRed" id="65497" width="10" height="10" line_attributes="lnSolidBlack" fill_attributes="flaFalse" ellipse_type="closed" start_angle="0" end_angle="180"/>
  <outputstring name="osPtoFront" id="65499" width="62" height="10" font_attributes="fta6x8" background_colour="white" options="transparent+autowrap" horizontal_justification="left" vertical_justification="top" value="PTO Front:" length="10" auto_set_length="1" variable_reference="NULL"/>
  <outputstring name="osCmS" id="65500" width="30" height="10" font_attributes="fta6x8" background_colour="white" options="transparent+autowrap" horizontal_justification="left" vertical_justification="top" value="cm/s" length="4" auto_set_length="1" variable_reference="NULL"/>
  <outputnumber name="onMaxPowerTime" id="65502" width="40" height="10" font_attributes="fta6x8" background_colour="white" options="transparent" number_of_decimals="0" format="fixed" horizontal_justification="right" vertical_justification="top" offset="0" scale="1" value="0" variable_reference="nvMaxPowerTime"/>
  <objectpointer name="opKeySwitch" id="65503" value="elStateRed"/>
  <outputstring name="osKeySwitch" id="65504" width="100" height="9" font_attributes="fta6x8" background_colour="white" options="transparent+autowrap" horizontal_justification="left" vertical_justification="top" value="Key Switch State:" length="17" auto_set_length="1" variable_reference="NULL"/>
  <outputnumber name="onTimeM" id="65505" width="20" height="10" font_attributes="fta6x8" background_colour="white" options="transparent" number_of_decimals="0" format="fixed" horizontal_justification="middle" vertical_justification="top" offset="0" scale="1" value="0" variable_reference="nvMin"/>
  <outputstring name="osMaskTecu" id="65506" width="80" height="15" font_attributes="fta8x8" background_colour="white" options="transparent+autowrap" horizontal_justification="middle" vertical_justification="top" value="TECU" length="4" auto_set_length="1" variable_reference="NULL"/>
  <numbervariable name="nvSec" id="65508" value="0"/>
  <numbervariable name="nvMin" id="65509" value="0"/>
  <outputstring name="osNavTECU" id="65510" width="60" height="32" font_attributes="fta8x12_SK" background_colour="white" options="autowrap" horizontal_justification="middle" vertical_justification="top" value="TECU" length="4" auto_set_length="1" variable_reference="NULL"/>
  <outputstring name="osNavTimePos" id="65511" width="60" height="32" font_attributes="fta8x12_SK" background_colour="white" options="autowrap" horizontal_justification="middle" vertical_justification="top" value="GpsSensor" length="9" auto_set_length="1" variable_reference="NULL"/>
  <outputstring name="osNavAbout" id="65512" width="60" height="32" font_attributes="fta8x12_SK" background_colour="white" options="autowrap" horizontal_justification="middle" vertical_justification="top" value="About" length="5" auto_set_length="1" variable_reference="NULL"/>
  <key name="keyNavTECU" id="65513" background_colour="white" key_code="254">
    <include_macro name="macroChangeMaskTecu" event="on_key_press"/>
    <include_object name="picKeyNavTecu" pos_x="10" pos_y="4"/>
  </key>
  <numbervariable name="nvHr" id="65514" value="0"/>
  <key name="keyNavTimePos" id="65515" background_colour="white" key_code="255">
    <include_macro name="macroChangeMaskTimePos" event="on_key_press"/>
    <include_object name="picKeyNavTimePos" pos_x="11" pos_y="6"/>
  </key>
  <softkeymask name="skmDisplay" id="65516" background_colour="209">
    <include_object name="keyNavAbout"/>
    <include_object name="keyNavTimePos"/>
    <include_object name="keyNavTECU"/>
  </softkeymask>
  <outputstring name="osMaskTimePos" id="65517" width="80" height="15" font_attributes="fta8x8" background_colour="white" options="transparent+autowrap" horizontal_justification="middle" vertical_justification="top" value="GPS Sensor" length="10" auto_set_length="1" variable_reference="NULL"/>
  <rectangle name="recLogoFrame" id="65518" width="200" height="33" line_attributes="lnSolidBlack" fill_attributes="flaLogo" line_suppression="none"/>
  <meter name="mtrSpeed" id="65522" width="56" min_value="0" max_value="300" needle_colour="19" border_colour="black" arc_and_tick_colour="black" number_of_ticks="30" options="arc+ticks+clockwise" start_angle="0" end_angle="90" value="0" variable_reference="nvSpeedReal" height="56"/>
  <key name="keyNavAbout" id="65523" background_colour="white" key_code="252">
    <include_macro name="macroChangeMaskAbout" event="on_key_press"/>
    <include_object name="picKeyNavAbout" pos_x="10" pos_y="5"/>
  </key>
  <outputnumber name="onTimeH" id="65524" width="20" height="10" font_attributes="fta6x8" background_colour="white" options="transparent" number_of_decimals="0" format="fixed" horizontal_justification="middle" vertical_justification="top" offset="0" scale="1" value="0" variable_reference="nvHr"/>
  <numbervariable name="nvLon" id="65525" value="0"/>
  <numbervariable name="nvLat" id="65526" value="0"/>
  <outputnumber name="onLon" id="65527" width="60" height="10" font_attributes="fta6x8" background_colour="white" options="transparent" number_of_decimals="0" format="fixed" horizontal_justification="right" vertical_justification="top" offset="0" scale="1" value="0" variable_reference="nvLon"/>
  <outputstring name="osLon" id="65528" width="60" height="10" font_attributes="fta6x8" background_colour="white" options="transparent+autowrap" horizontal_justification="right" vertical_justification="top" value="Longitude:" length="10" auto_set_length="1" variable_reference="NULL"/>
  <outputnumber name="onLat" id="65529" width="50" height="10" font_attributes="fta6x8" background_colour="white" options="transparent" number_of_decimals="0" format="fixed" horizontal_justification="left" vertical_justification="top" offset="0" scale="1" value="0" variable_reference="nvLat"/>
  <outputstring name="osLat" id="65530" width="57" height="8" font_attributes="fta6x8" background_colour="white" options="transparent+autowrap" horizontal_justification="left" vertical_justification="top" value="Latitude:" length="9" auto_set_length="1" variable_reference="NULL"/>
  <outputstring name="osMaxPower" id="65531" width="100" height="8" font_attributes="fta6x8" background_colour="white" options="transparent+autowrap" horizontal_justification="left" vertical_justification="top" value="Max Power Time:" length="15" auto_set_length="1" variable_reference="NULL"/>
  <outputstring name="osTime" id="65533" language="*" width="100" height="10" font_attributes="fta6x8" background_colour="white" options="transparent+autowrap" horizontal_justification="left" vertical_justification="top" value="" length="0" auto_set_length="1" variable_reference="NULL"/>
</objectpool>
